commanderbot_ext/__init__.py
commanderbot_ext/ext/__init__.py
commanderbot_ext/ext/automod/__init__.py
commanderbot_ext/ext/automod/actions/__init__.py
commanderbot_ext/ext/automod/actions/abc/__init__.py
commanderbot_ext/ext/automod/actions/abc/add_roles_to_target_base.py
commanderbot_ext/ext/automod/actions/abc/remove_roles_from_target_base.py
commanderbot_ext/ext/automod/actions/add_reactions.py
commanderbot_ext/ext/automod/actions/add_roles_to_actor.py
commanderbot_ext/ext/automod/actions/add_roles_to_author.py
commanderbot_ext/ext/automod/actions/delete_message.py
commanderbot_ext/ext/automod/actions/log_message.py
commanderbot_ext/ext/automod/actions/remove_all_reactions.py
commanderbot_ext/ext/automod/actions/remove_own_reactions.py
commanderbot_ext/ext/automod/actions/remove_reactions.py
commanderbot_ext/ext/automod/actions/remove_roles_from_actor.py
commanderbot_ext/ext/automod/actions/remove_roles_from_author.py
commanderbot_ext/ext/automod/actions/reply_to_message.py
commanderbot_ext/ext/automod/actions/send_message.py
commanderbot_ext/ext/automod/actions/throw_error.py
commanderbot_ext/ext/automod/automod_action.py
commanderbot_ext/ext/automod/automod_cog.py
commanderbot_ext/ext/automod/automod_condition.py
commanderbot_ext/ext/automod/automod_data.py
commanderbot_ext/ext/automod/automod_entity.py
commanderbot_ext/ext/automod/automod_event.py
commanderbot_ext/ext/automod/automod_guild_state.py
commanderbot_ext/ext/automod/automod_json_store.py
commanderbot_ext/ext/automod/automod_log_options.py
commanderbot_ext/ext/automod/automod_options.py
commanderbot_ext/ext/automod/automod_rule.py
commanderbot_ext/ext/automod/automod_state.py
commanderbot_ext/ext/automod/automod_store.py
commanderbot_ext/ext/automod/automod_trigger.py
commanderbot_ext/ext/automod/conditions/__init__.py
commanderbot_ext/ext/automod/conditions/abc/__init__.py
commanderbot_ext/ext/automod/conditions/abc/target_account_age_base.py
commanderbot_ext-0.15.0.dist-info/LICENSE.txt
commanderbot_ext-0.15.0.dist-info/WHEEL
commanderbot_ext-0.15.0.dist-info/METADATA
commanderbot_ext-0.15.0.dist-info/RECORD
