Metadata-Version: 2.1
Name: commanderbot-ext
Version: 0.15.0
Summary: A collection of cogs and extensions for discord.py bots.
Home-page: https://github.com/CommanderBot-Dev/commanderbot-ext
License: MIT
Keywords: discord,bot
Author: Arcensoth
Author-email: arcensoth@gmail.com
Requires-Python: >=3.8,<4.0
Classifier: License :: OSI Approved :: MIT License
Classifier: Programming Language :: Python :: 3
Classifier: Programming Language :: Python :: 3.8
Classifier: Programming Language :: Python :: 3.9
Classifier: Programming Language :: Python :: 3.10
Requires-Dist: PyYAML (>=5.4.1,<6.0.0)
Requires-Dist: SQLAlchemy (>=1.4.9,<2.0.0)
Requires-Dist: aiohttp (>=3.7.4,<4.0.0)
Requires-Dist: aiosqlite (>=0.17.0,<0.18.0)
Requires-Dist: beet (>=0.32.1)
Requires-Dist: commanderbot (>=0.9.0,<0.10.0)
Requires-Dist: discord.py (>=1.7.1,<2.0.0)
Requires-Dist: emoji (>=1.4.2,<2.0.0)
Requires-Dist: lectern (>=0.14.0)
Project-URL: Repository, https://github.com/CommanderBot-Dev/commanderbot-ext
